Metadata-Version: 2.1
Name: hack4u_eg4n
Version: 0.1.2
Summary: Una biblioteca para consultar los cursos de hack4u.
Home-page: https://hack4u.io
Author: Ernesto Andrés
